tsa_core/__init__.py
tsa_core-0.0.1.dist-info/METADATA
tsa_core-0.0.1.dist-info/WHEEL
tsa_core-0.0.1.dist-info/top_level.txt
tsa_core-0.0.1.dist-info/RECORD
