Metadata-Version: 2.4
Name: tsa-core
Version: 0.0.1
Summary: Temporal State Abstraction Core — The OS for AI Agents
Author-email: Your Name <you@yourdomain.com>
License: MIT
Project-URL: Homepage, https://tsacore.ai
Project-URL: Repository, https://github.com/tsa-core/tsa-core
Keywords: ai,temporal,agents,memory,tsa,state
Classifier: Programming Language :: Python :: 3
Classifier: License :: OSI Approved :: MIT License
Requires-Python: >=3.8
